pytermcolors/__init__.py
pytermcolors/pytermcolors.py
pytermcolors-1.0.0.dist-info/licenses/LICENSE
pytermcolors-1.0.0.dist-info/METADATA
pytermcolors-1.0.0.dist-info/WHEEL
pytermcolors-1.0.0.dist-info/top_level.txt
pytermcolors-1.0.0.dist-info/RECORD
