Metadata-Version: 2.4
Name: pytermcolors
Version: 1.0.0
Summary: Terminal output styling - ANSI colors and styles for Python
Author-email: Etsor <etsorucheba@gmail.com>
License-Expression: MIT
Project-URL: Homepage, https://github.com/Etsor/PyTermColors
Project-URL: Repository, https://github.com/Etsor/PyTermColors
Keywords: terminal,ansi,colors,cli,styling
Classifier: Programming Language :: Python :: 3
Classifier: Operating System :: OS Independent
Requires-Python: >=3.6
License-File: LICENSE
Dynamic: license-file
